vatglobaldevopsinterview/__init__.py
vatglobaldevopsinterview/asgi.py
vatglobaldevopsinterview/settings.py
vatglobaldevopsinterview/urls.py
vatglobaldevopsinterview/wsgi.py
vatglobaldevopsinterview-0.1.0.dist-info/WHEEL
vatglobaldevopsinterview-0.1.0.dist-info/METADATA
vatglobaldevopsinterview-0.1.0.dist-info/RECORD
